[
    { "n": "全省", "id": "0" },
    { "n": "潮州市", "g": { "left": "2085px", "top": "38.94px" }, "g1": { "left": "2485px", "top": "1137.94px" }, "id": "1" },
    { "n": "广州市", "g": { "left": "700.38px", "top": "270.337px" }, "g1": { "left": "1549.5px", "top": "1270.001px" }, "id": "2" },
    { "n": "揭阳市", "g": { "left": "2050.99px", "top": "322.94px" }, "g1": { "left": "2250.78px", "top": "1322.94px" }, "id": "3" },
    { "n": "深圳市", "g": { "left": "468.78px", "top": "600.52px" }, "g1": { "left": "1668.78px", "top": "1600.518px" }, "id": "4" },
    { "n": "汕尾市", "g": { "left": "1850.99px", "top": "600.94px" }, "g1": { "left": "2050.78px", "top": "1500.94px" }, "id": "5" },
    { "n": "佛山市", "g": { "left": "1200.31px", "top": "900.055px" }, "g1": { "left": "1400.78px", "top": "1500.055px" }, "id": "6" },
    { "n": "湛江市", "g": { "left": "2070.99px", "top": "900.94px" }, "g1": { "left": "370.78px", "top": "2400.94px" }, "id": "7" },
    { "n": "东莞市", "g": { "left": "800.62px", "top": "1186px" }, "g1": { "left": "1600.38px", "top": "1486px" }, "id": "8" },
    { "n": "茂名市", "g": { "left": "620.99px", "top": "1900.94px" }, "g1": { "left": "620.78px", "top": "1900.94px" }, "id": "9" },
    { "n": "中山市", "g": { "left": "1500.86px", "top": "1652.18px" }, "g1": { "left": "1500.86px", "top": "1652.02px" }, "id": "10" },
    { "n": "阳江市", "g": { "left": "945.99px", "top": "1900.94px" }, "g1": { "left": "945.78px", "top": "1900.94px" }, "id": "11" },
    { "n": "珠海市", "g": { "left": "1455.5px", "top": "1850.22px" }, "g1": { "left": "1455.5px", "top": "1850.22px" }, "id": "12" },
    { "n": "云浮市", "g": { "left": "920.99px", "top": "1550.94px" }, "g1": { "left": "920.78px", "top": "1550.94px" }, "id": "13" },
    { "n": "江门市", "g": { "left": "1278.72px", "top": "1735.22px" }, "g1": { "left": "1278.5px", "top": "1735.22px" }, "id": "14" },
    { "n": "韶关市", "g": { "left": "1420.99px", "top": "700.94px" }, "g1": { "left": "1420.78px", "top": "700.94px" }, "id": "15" },
    { "n": "肇庆市", "g": { "left": "1150.77px", "top": "1150.13px" }, "g1": { "left": "1150.5px", "top": "1150.13px" }, "id": "16" },
    { "n": "清远市", "g": { "left": "1327.99px", "top": "900.94px" }, "g1": { "left": "1327.78px", "top": "900.94px" }, "id": "17" },
    { "n": "惠州市", "g": { "left": "1778.53px", "top": "1350.75px" }, "g1": { "left": "1778.53px", "top": "1350.75px" }, "id": "18" },
    { "n": "梅州市", "g": { "left": "2220.99px", "top": "900.94px" }, "g1": { "left": "2220.78px", "top": "900.94px" }, "id": "19" },
    { "n": "汕头市", "g": { "left": "2500.38px", "top": "1354.02px" }, "g1": { "left": "2500.38px", "top": "1354.02px" }, "id": "20" },
    { "n": "河源市", "g": { "left": "1900.99px", "top": "1000.94px" }, "g1": { "left": "1900.78px", "top": "1000.94px" }, "id": "21" }
]
